MANIFEST.in
README.rst
setup.cfg
setup.py
hopak/__init__.py
hopak/controllers.py
hopak/exceptions.py
hopak/fields.py
hopak/forms.py
hopak/loader.py
hopak/models.py
hopak/registry.py
hopak/utils.py
hopak/widgets.py
hopak.egg-info/PKG-INFO
hopak.egg-info/SOURCES.txt
hopak.egg-info/dependency_links.txt
hopak.egg-info/requires.txt
hopak.egg-info/top_level.txt
hopak/ds/__init__.py
hopak/ds/base.py
hopak/ds/mongo.py
hopak/templates/form.html
hopak/templates/form_old.html
hopak/templates/widgets/base_widget.html
hopak/templates/widgets/boolean.html
hopak/templates/widgets/checkbox.html
hopak/templates/widgets/email.html
hopak/templates/widgets/markdown.html
hopak/templates/widgets/password.html
hopak/templates/widgets/pricerange.html
hopak/templates/widgets/select.html
hopak/templates/widgets/string.html
hopak/templates/widgets/text.html
hopak/templates/widgets/timerange.html