Metadata-Version: 1.1
Name: hopak
Version: 0.5.1
Summary: hopak framework base package
Home-page: https://github.com/xen/hopak
Author: Mikhail Kashkin
Author-email: mkashkin@gmail.com
License: BSD
Platform: UNKNOWN
Classifier: Development Status :: 4 - Beta
Classifier: Intended Audience :: Developers
Classifier: License :: OSI Approved :: BSD License
Classifier: Operating System :: OS Independent
Classifier: Programming Language :: Python
Classifier: Programming Language :: Python :: 2.7
Classifier: Programming Language :: Python :: 3.3
Classifier: Topic :: Software Development :: Libraries :: Python Modules
